jdb_python/__init__.py
jdb_python/functions.py
jdb_python-0.0.1.dist-info/METADATA
jdb_python-0.0.1.dist-info/WHEEL
jdb_python-0.0.1.dist-info/top_level.txt
jdb_python-0.0.1.dist-info/RECORD
