Metadata-Version: 2.1
Name: jdb_python
Version: 0.0.1
Summary: Package of mine to do a JSON based simple database!
